__init__.py
main.py
nest_folder/my_nest.py
python_course_rpg-0.0.6.dist-info/METADATA
python_course_rpg-0.0.6.dist-info/WHEEL
python_course_rpg-0.0.6.dist-info/top_level.txt
python_course_rpg-0.0.6.dist-info/RECORD
