Metadata-Version: 2.1
Name: python-course-rpg
Version: 0.0.6
Summary: My package description
Author-email: Sagar <some-email@gmail.com>
License: MIT
Keywords: one,two
Classifier: Programming Language :: Python :: 3
Requires-Python: >=3.7
Requires-Dist: numpy
Provides-Extra: dev
Requires-Dist: python-course-rpg[release,static-code-qa,test] ; extra == 'dev'
Provides-Extra: release
Requires-Dist: build ; extra == 'release'
Requires-Dist: twine ; extra == 'release'
Provides-Extra: static-code-qa
Requires-Dist: pre-commit ; extra == 'static-code-qa'
Provides-Extra: test
Requires-Dist: pytest ; extra == 'test'
Requires-Dist: pytest-cov ; extra == 'test'
